subunitdetails
