Metadata-Version: 1.1
Name: subunitdetails
Version: 0.0.3
Summary: SubUnit Details Parser - Test Detail attachment extractor.
Home-page: https://github.com/cgoldberg/subunitdetails
Author: Corey Goldberg
Author-email: cgoldberg _at_ gmail.com
License: GNU GPLv3
Download-URL: http://pypi.python.org/pypi/subunitdetails
Keywords: subunit,parser,unittest,testtools,testing
Platform: UNKNOWN
Classifier: Development Status :: 4 - Beta
Classifier: Environment :: Console
Classifier: Intended Audience :: Developers
Classifier: License :: OSI Approved :: GNU General Public License v3 (GPLv3)
Classifier: Topic :: Office/Business :: Financial :: Investment
Classifier: Operating System :: OS Independent
Classifier: Programming Language :: Python :: 3
Classifier: Programming Language :: Python :: 3.2
Classifier: Programming Language :: Python :: 3.3
Classifier: Programming Language :: Python :: 3.4
Classifier: Topic :: Software Development :: Testing
